cymove/__init__.pxd
cymove/__init__.py
cymove-1.0.2.dist-info/LICENSE
cymove-1.0.2.dist-info/METADATA
cymove-1.0.2.dist-info/WHEEL
cymove-1.0.2.dist-info/top_level.txt
cymove-1.0.2.dist-info/RECORD
