Metadata-Version: 2.1
Name: cymove
Version: 1.0.2
Summary: std::move wrapper for cython
Home-page: https://github.com/ozars/cymove
Author: Omer Ozarslan
License: MIT
Platform: UNKNOWN
Classifier: Intended Audience :: Developers
Classifier: License :: OSI Approved :: MIT License
Classifier: Operating System :: MacOS
Classifier: Operating System :: Microsoft :: Windows
Classifier: Operating System :: POSIX :: Linux
Classifier: Programming Language :: C++
Classifier: Programming Language :: Cython
